Metadata-Version: 2.1
Name: bigfishes
Version: 0.0.1
Summary: Midterm package
Home-page: https://github.com/wnelso18/bigfishes
Author: Will Nelson
Author-email: wnelso18@vols.utk.edu
License: MIT license
Keywords: bigfishes
Classifier: Development Status :: 2 - Pre-Alpha
Classifier: Intended Audience :: Developers
Classifier: License :: OSI Approved :: MIT License
Classifier: Natural Language :: English
Classifier: Programming Language :: Python :: 3
Classifier: Programming Language :: Python :: 3.7
Classifier: Programming Language :: Python :: 3.8
Classifier: Programming Language :: Python :: 3.9
Classifier: Programming Language :: Python :: 3.10
Requires-Python: >=3.7
License-File: LICENSE
